epwechat/__init__.py
epwechat/access/__init__.py
epwechat/access/token.py
epwechat/cache/__init__.py
epwechat/cache/token_cache.py
epwechat/send_msg/__init__.py
epwechat/send_msg/send_msg.py
epwechat-1.0.0.dist-info/METADATA
epwechat-1.0.0.dist-info/WHEEL
epwechat-1.0.0.dist-info/top_level.txt
epwechat-1.0.0.dist-info/RECORD
