Metadata-Version: 2.1
Name: epwechat
Version: 1.0.0
Summary: This is a enterprise wechat of the setup
Home-page: UNKNOWN
Author: Allen
Author-email: ithongchou@163.com
License: UNKNOWN
Platform: UNKNOWN
Requires-Dist: requests
Requires-Dist: redis
